{
  "fightId": "peterodriguez_vs_thembagorimbo_2024-02-03",
  "fightTitle": "Pete Rodriguez vs Themba Gorimbo",
  "commenceTime": null,
  "startTime": "2024-02-03T22:05:38Z",
  "endTime": "2024-02-03T23:05:38Z",
  "dataPoints": 5,
  "oddsHistory": [
    {
      "timestamp": "2024-02-03T22:05:38Z",
      "fighter1": {
        "name": "Pete Rodriguez",
        "numericOdds": 170
      },
      "fighter2": {
        "name": "Themba Gorimbo",
        "numericOdds": -205
      }
    },
    {
      "timestamp": "2024-02-03T22:20:38Z",
      "fighter1": {
        "name": "Pete Rodriguez",
        "numericOdds": 170
      },
      "fighter2": {
        "name": "Themba Gorimbo",
        "numericOdds": -205
      }
    },
    {
      "timestamp": "2024-02-03T22:35:38Z",
      "fighter1": {
        "name": "Pete Rodriguez",
        "numericOdds": 160
      },
      "fighter2": {
        "name": "Themba Gorimbo",
        "numericOdds": -192
      }
    },
    {
      "timestamp": "2024-02-03T22:50:38Z",
      "fighter1": {
        "name": "Pete Rodriguez",
        "numericOdds": 160
      },
      "fighter2": {
        "name": "Themba Gorimbo",
        "numericOdds": -192
      }
    },
    {
      "timestamp": "2024-02-03T23:05:38Z",
      "fighter1": {
        "name": "Pete Rodriguez",
        "numericOdds": 160
      },
      "fighter2": {
        "name": "Themba Gorimbo",
        "numericOdds": -192
      }
    }
  ]
}