{
  "fightId": "beneildariush_vs_quillansalkilld",
  "fightTitle": "Connected but no betting buttons found",
  "commenceTime": null,
  "startTime": "2026-05-02T13:21:18.853Z",
  "endTime": "2026-05-02T13:23:52.220Z",
  "dataPoints": 104,
  "oddsHistory": [
    {
      "timestamp": "2026-05-02T13:21:18.853Z",
      "fighter1": {
        "name": "Beneil Dariush",
        "odds": "+330",
        "numericOdds": 330
      },
      "fighter2": {
        "name": "Quillan Salkilld",
        "odds": "-480",
        "numericOdds": -480
      },
      "isLocked": false,
      "extractionId": 35
    },
    {
      "timestamp": "2026-05-02T13:21:21.856Z",
      "fighter1": {
        "name": "Beneil Dariush",
        "odds": "+330",
        "numericOdds": 330
      },
      "fighter2": {
        "name": "Quillan Salkilld",
        "odds": "-480",
        "numericOdds": -480
      },
      "isLocked": false,
      "extractionId": 2
    },
    {
      "timestamp": "2026-05-02T13:21:24.861Z",
      "fighter1": {
        "name": "Beneil Dariush",
        "odds": "+270",
        "numericOdds": 270
      },
      "fighter2": {
        "name": "Quillan Salkilld",
        "odds": "-380",
        "numericOdds": -380
      },
      "isLocked": false,
      "extractionId": 3
    },
    {
      "timestamp": "2026-05-02T13:21:27.876Z",
      "fighter1": {
        "name": "Beneil Dariush",
        "odds": "+270",
        "numericOdds": 270
      },
      "fighter2": {
        "name": "Quillan Salkilld",
        "odds": "-380",
        "numericOdds": -380
      },
      "isLocked": false,
      "extractionId": 4
    },
    {
      "timestamp": "2026-05-02T13:21:30.880Z",
      "fighter1": {
        "name": "Beneil Dariush",
        "odds": "+225",
        "numericOdds": 225
      },
      "fighter2": {
        "name": "Quillan Salkilld",
        "odds": "-310",
        "numericOdds": -310
      },
      "isLocked": false,
      "extractionId": 5
    },
    {
      "timestamp": "2026-05-02T13:21:33.883Z",
      "fighter1": {
        "name": "Beneil Dariush",
        "odds": "+184",
        "numericOdds": 184
      },
      "fighter2": {
        "name": "Quillan Salkilld",
        "odds": "-240",
        "numericOdds": -240
      },
      "isLocked": false,
      "extractionId": 6
    },
    {
      "timestamp": "2026-05-02T13:21:36.892Z",
      "fighter1": {
        "name": "Beneil Dariush",
        "odds": "+184",
        "numericOdds": 184
      },
      "fighter2": {
        "name": "Quillan Salkilld",
        "odds": "-240",
        "numericOdds": -240
      },
      "isLocked": false,
      "extractionId": 7
    },
    {
      "timestamp": "2026-05-02T13:21:39.895Z",
      "fighter1": {
        "name": "Beneil Dariush",
        "odds": "+158",
        "numericOdds": 158
      },
      "fighter2": {
        "name": "Quillan Salkilld",
        "odds": "-205",
        "numericOdds": -205
      },
      "isLocked": false,
      "extractionId": 8
    },
    {
      "timestamp": "2026-05-02T13:21:42.907Z",
      "fighter1": {
        "name": "Beneil Dariush",
        "odds": "+158",
        "numericOdds": 158
      },
      "fighter2": {
        "name": "Quillan Salkilld",
        "odds": "-205",
        "numericOdds": -205
      },
      "isLocked": false,
      "extractionId": 9
    },
    {
      "timestamp": "2026-05-02T13:21:45.915Z",
      "fighter1": {
        "name": "Beneil Dariush",
        "odds": "+158",
        "numericOdds": 158
      },
      "fighter2": {
        "name": "Quillan Salkilld",
        "odds": "-205",
        "numericOdds": -205
      },
      "isLocked": false,
      "extractionId": 10
    },
    {
      "timestamp": "2026-05-02T13:21:48.926Z",
      "fighter1": {
        "name": "Beneil Dariush",
        "odds": "+158",
        "numericOdds": 158
      },
      "fighter2": {
        "name": "Quillan Salkilld",
        "odds": "-205",
        "numericOdds": -205
      },
      "isLocked": false,
      "extractionId": 11
    },
    {
      "timestamp": "2026-05-02T13:21:51.937Z",
      "fighter1": {
        "name": "Beneil Dariush",
        "odds": "+158",
        "numericOdds": 158
      },
      "fighter2": {
        "name": "Quillan Salkilld",
        "odds": "-205",
        "numericOdds": -205
      },
      "isLocked": false,
      "extractionId": 12
    },
    {
      "timestamp": "2026-05-02T13:21:54.945Z",
      "fighter1": {
        "name": "Beneil Dariush",
        "odds": "+158",
        "numericOdds": 158
      },
      "fighter2": {
        "name": "Quillan Salkilld",
        "odds": "-205",
        "numericOdds": -205
      },
      "isLocked": false,
      "extractionId": 13
    },
    {
      "timestamp": "2026-05-02T13:21:57.950Z",
      "fighter1": {
        "name": "Beneil Dariush",
        "odds": "+158",
        "numericOdds": 158
      },
      "fighter2": {
        "name": "Quillan Salkilld",
        "odds": "-205",
        "numericOdds": -205
      },
      "isLocked": false,
      "extractionId": 14
    },
    {
      "timestamp": "2026-05-02T13:22:00.960Z",
      "fighter1": {
        "name": "Beneil Dariush",
        "odds": "+172",
        "numericOdds": 172
      },
      "fighter2": {
        "name": "Quillan Salkilld",
        "odds": "-225",
        "numericOdds": -225
      },
      "isLocked": false,
      "extractionId": 15
    },
    {
      "timestamp": "2026-05-02T13:22:03.960Z",
      "fighter1": {
        "name": "Beneil Dariush",
        "odds": "+172",
        "numericOdds": 172
      },
      "fighter2": {
        "name": "Quillan Salkilld",
        "odds": "-225",
        "numericOdds": -225
      },
      "isLocked": false,
      "extractionId": 16
    },
    {
      "timestamp": "2026-05-02T13:22:06.969Z",
      "fighter1": {
        "name": "Beneil Dariush",
        "odds": "+172",
        "numericOdds": 172
      },
      "fighter2": {
        "name": "Quillan Salkilld",
        "odds": "-225",
        "numericOdds": -225
      },
      "isLocked": false,
      "extractionId": 17
    },
    {
      "timestamp": "2026-05-02T13:22:09.974Z",
      "fighter1": {
        "name": "Beneil Dariush",
        "odds": "+152",
        "numericOdds": 152
      },
      "fighter2": {
        "name": "Quillan Salkilld",
        "odds": "-196",
        "numericOdds": -196
      },
      "isLocked": false,
      "extractionId": 18
    },
    {
      "timestamp": "2026-05-02T13:22:12.982Z",
      "fighter1": {
        "name": "Beneil Dariush",
        "odds": "+152",
        "numericOdds": 152
      },
      "fighter2": {
        "name": "Quillan Salkilld",
        "odds": "-196",
        "numericOdds": -196
      },
      "isLocked": false,
      "extractionId": 19
    },
    {
      "timestamp": "2026-05-02T13:22:15.985Z",
      "fighter1": {
        "name": "Beneil Dariush",
        "odds": "+152",
        "numericOdds": 152
      },
      "fighter2": {
        "name": "Quillan Salkilld",
        "odds": "-196",
        "numericOdds": -196
      },
      "isLocked": false,
      "extractionId": 20
    },
    {
      "timestamp": "2026-05-02T13:22:18.992Z",
      "fighter1": {
        "name": "Beneil Dariush",
        "odds": "+152",
        "numericOdds": 152
      },
      "fighter2": {
        "name": "Quillan Salkilld",
        "odds": "-196",
        "numericOdds": -196
      },
      "isLocked": false,
      "extractionId": 21
    },
    {
      "timestamp": "2026-05-02T13:22:21.999Z",
      "fighter1": {
        "name": "Beneil Dariush",
        "odds": "+152",
        "numericOdds": 152
      },
      "fighter2": {
        "name": "Quillan Salkilld",
        "odds": "-196",
        "numericOdds": -196
      },
      "isLocked": false,
      "extractionId": 22
    },
    {
      "timestamp": "2026-05-02T13:22:25.007Z",
      "fighter1": {
        "name": "Beneil Dariush",
        "odds": "+152",
        "numericOdds": 152
      },
      "fighter2": {
        "name": "Quillan Salkilld",
        "odds": "-196",
        "numericOdds": -196
      },
      "isLocked": false,
      "extractionId": 23
    },
    {
      "timestamp": "2026-05-02T13:22:28.012Z",
      "fighter1": {
        "name": "Beneil Dariush",
        "odds": "+152",
        "numericOdds": 152
      },
      "fighter2": {
        "name": "Quillan Salkilld",
        "odds": "-196",
        "numericOdds": -196
      },
      "isLocked": false,
      "extractionId": 24
    },
    {
      "timestamp": "2026-05-02T13:22:31.020Z",
      "fighter1": {
        "name": "Beneil Dariush",
        "odds": "+152",
        "numericOdds": 152
      },
      "fighter2": {
        "name": "Quillan Salkilld",
        "odds": "-196",
        "numericOdds": -196
      },
      "isLocked": false,
      "extractionId": 25
    },
    {
      "timestamp": "2026-05-02T13:22:34.027Z",
      "fighter1": {
        "name": "Beneil Dariush",
        "odds": "+158",
        "numericOdds": 158
      },
      "fighter2": {
        "name": "Quillan Salkilld",
        "odds": "-205",
        "numericOdds": -205
      },
      "isLocked": false,
      "extractionId": 26
    },
    {
      "timestamp": "2026-05-02T13:22:37.034Z",
      "fighter1": {
        "name": "Beneil Dariush",
        "odds": "+158",
        "numericOdds": 158
      },
      "fighter2": {
        "name": "Quillan Salkilld",
        "odds": "-205",
        "numericOdds": -205
      },
      "isLocked": false,
      "extractionId": 27
    },
    {
      "timestamp": "2026-05-02T13:22:40.035Z",
      "fighter1": {
        "name": "Beneil Dariush",
        "odds": "+158",
        "numericOdds": 158
      },
      "fighter2": {
        "name": "Quillan Salkilld",
        "odds": "-205",
        "numericOdds": -205
      },
      "isLocked": false,
      "extractionId": 28
    },
    {
      "timestamp": "2026-05-02T13:22:43.045Z",
      "fighter1": {
        "name": "Beneil Dariush",
        "odds": "+158",
        "numericOdds": 158
      },
      "fighter2": {
        "name": "Quillan Salkilld",
        "odds": "-205",
        "numericOdds": -205
      },
      "isLocked": false,
      "extractionId": 29
    },
    {
      "timestamp": "2026-05-02T13:22:46.053Z",
      "fighter1": {
        "name": "Beneil Dariush",
        "odds": "+158",
        "numericOdds": 158
      },
      "fighter2": {
        "name": "Quillan Salkilld",
        "odds": "-205",
        "numericOdds": -205
      },
      "isLocked": false,
      "extractionId": 30
    },
    {
      "timestamp": "2026-05-02T13:22:49.054Z",
      "fighter1": {
        "name": "Beneil Dariush",
        "odds": "+158",
        "numericOdds": 158
      },
      "fighter2": {
        "name": "Quillan Salkilld",
        "odds": "-205",
        "numericOdds": -205
      },
      "isLocked": false,
      "extractionId": 31
    },
    {
      "timestamp": "2026-05-02T13:22:52.068Z",
      "fighter1": {
        "name": "Beneil Dariush",
        "odds": "+158",
        "numericOdds": 158
      },
      "fighter2": {
        "name": "Quillan Salkilld",
        "odds": "-205",
        "numericOdds": -205
      },
      "isLocked": false,
      "extractionId": 32
    },
    {
      "timestamp": "2026-05-02T13:22:55.080Z",
      "fighter1": {
        "name": "Beneil Dariush",
        "odds": "+160",
        "numericOdds": 160
      },
      "fighter2": {
        "name": "Quillan Salkilld",
        "odds": "-210",
        "numericOdds": -210
      },
      "isLocked": false,
      "extractionId": 33
    },
    {
      "timestamp": "2026-05-02T13:22:58.084Z",
      "fighter1": {
        "name": "Beneil Dariush",
        "odds": "+160",
        "numericOdds": 160
      },
      "fighter2": {
        "name": "Quillan Salkilld",
        "odds": "-210",
        "numericOdds": -210
      },
      "isLocked": false,
      "extractionId": 34
    },
    {
      "timestamp": "2026-05-02T13:23:01.098Z",
      "fighter1": {
        "name": "Beneil Dariush",
        "odds": "+164",
        "numericOdds": 164
      },
      "fighter2": {
        "name": "Quillan Salkilld",
        "odds": "-215",
        "numericOdds": -215
      },
      "isLocked": false,
      "extractionId": 35
    },
    {
      "timestamp": "2026-05-02T13:23:04.100Z",
      "fighter1": {
        "name": "Beneil Dariush",
        "odds": "+164",
        "numericOdds": 164
      },
      "fighter2": {
        "name": "Quillan Salkilld",
        "odds": "-215",
        "numericOdds": -215
      },
      "isLocked": false,
      "extractionId": 36
    },
    {
      "timestamp": "2026-05-02T13:23:07.112Z",
      "fighter1": {
        "name": "Beneil Dariush",
        "odds": "+164",
        "numericOdds": 164
      },
      "fighter2": {
        "name": "Quillan Salkilld",
        "odds": "-215",
        "numericOdds": -215
      },
      "isLocked": false,
      "extractionId": 37
    },
    {
      "timestamp": "2026-05-02T13:23:10.122Z",
      "fighter1": {
        "name": "Beneil Dariush",
        "odds": "+164",
        "numericOdds": 164
      },
      "fighter2": {
        "name": "Quillan Salkilld",
        "odds": "-215",
        "numericOdds": -215
      },
      "isLocked": false,
      "extractionId": 38
    },
    {
      "timestamp": "2026-05-02T13:23:13.126Z",
      "fighter1": {
        "name": "Beneil Dariush",
        "odds": "+164",
        "numericOdds": 164
      },
      "fighter2": {
        "name": "Quillan Salkilld",
        "odds": "-215",
        "numericOdds": -215
      },
      "isLocked": false,
      "extractionId": 39
    },
    {
      "timestamp": "2026-05-02T13:23:16.134Z",
      "fighter1": {
        "name": "Beneil Dariush",
        "odds": "+164",
        "numericOdds": 164
      },
      "fighter2": {
        "name": "Quillan Salkilld",
        "odds": "-215",
        "numericOdds": -215
      },
      "isLocked": false,
      "extractionId": 40
    },
    {
      "timestamp": "2026-05-02T13:23:19.134Z",
      "fighter1": {
        "name": "Beneil Dariush",
        "odds": "+164",
        "numericOdds": 164
      },
      "fighter2": {
        "name": "Quillan Salkilld",
        "odds": "-215",
        "numericOdds": -215
      },
      "isLocked": false,
      "extractionId": 41
    },
    {
      "timestamp": "2026-05-02T13:23:22.145Z",
      "fighter1": {
        "name": "Beneil Dariush",
        "odds": "+164",
        "numericOdds": 164
      },
      "fighter2": {
        "name": "Quillan Salkilld",
        "odds": "-215",
        "numericOdds": -215
      },
      "isLocked": false,
      "extractionId": 42
    },
    {
      "timestamp": "2026-05-02T13:23:25.158Z",
      "fighter1": {
        "name": "Beneil Dariush",
        "odds": "+164",
        "numericOdds": 164
      },
      "fighter2": {
        "name": "Quillan Salkilld",
        "odds": "-215",
        "numericOdds": -215
      },
      "isLocked": false,
      "extractionId": 43
    },
    {
      "timestamp": "2026-05-02T13:23:28.165Z",
      "fighter1": {
        "name": "Beneil Dariush",
        "odds": "+164",
        "numericOdds": 164
      },
      "fighter2": {
        "name": "Quillan Salkilld",
        "odds": "-215",
        "numericOdds": -215
      },
      "isLocked": false,
      "extractionId": 44
    },
    {
      "timestamp": "2026-05-02T13:23:31.166Z",
      "fighter1": {
        "name": "Beneil Dariush",
        "odds": "+164",
        "numericOdds": 164
      },
      "fighter2": {
        "name": "Quillan Salkilld",
        "odds": "-215",
        "numericOdds": -215
      },
      "isLocked": false,
      "extractionId": 45
    },
    {
      "timestamp": "2026-05-02T13:23:34.170Z",
      "fighter1": {
        "name": "Beneil Dariush",
        "odds": "+164",
        "numericOdds": 164
      },
      "fighter2": {
        "name": "Quillan Salkilld",
        "odds": "-215",
        "numericOdds": -215
      },
      "isLocked": false,
      "extractionId": 46
    },
    {
      "timestamp": "2026-05-02T13:23:37.183Z",
      "fighter1": {
        "name": "Beneil Dariush",
        "odds": "+164",
        "numericOdds": 164
      },
      "fighter2": {
        "name": "Quillan Salkilld",
        "odds": "-215",
        "numericOdds": -215
      },
      "isLocked": false,
      "extractionId": 47
    },
    {
      "timestamp": "2026-05-02T13:23:40.191Z",
      "fighter1": {
        "name": "Beneil Dariush",
        "odds": "+164",
        "numericOdds": 164
      },
      "fighter2": {
        "name": "Quillan Salkilld",
        "odds": "-215",
        "numericOdds": -215
      },
      "isLocked": false,
      "extractionId": 48
    },
    {
      "timestamp": "2026-05-02T13:23:43.193Z",
      "fighter1": {
        "name": "Beneil Dariush",
        "odds": "+164",
        "numericOdds": 164
      },
      "fighter2": {
        "name": "Quillan Salkilld",
        "odds": "-215",
        "numericOdds": -215
      },
      "isLocked": false,
      "extractionId": 49
    },
    {
      "timestamp": "2026-05-02T13:23:46.203Z",
      "fighter1": {
        "name": "Beneil Dariush",
        "odds": "+166",
        "numericOdds": 166
      },
      "fighter2": {
        "name": "Quillan Salkilld",
        "odds": "-215",
        "numericOdds": -215
      },
      "isLocked": false,
      "extractionId": 50
    },
    {
      "timestamp": "2026-05-02T13:23:49.208Z",
      "fighter1": {
        "name": "Beneil Dariush",
        "odds": "+166",
        "numericOdds": 166
      },
      "fighter2": {
        "name": "Quillan Salkilld",
        "odds": "-215",
        "numericOdds": -215
      },
      "isLocked": false,
      "extractionId": 51
    },
    {
      "timestamp": "2026-05-02T13:23:52.220Z",
      "fighter1": {
        "name": "Beneil Dariush",
        "odds": "+166",
        "numericOdds": 166
      },
      "fighter2": {
        "name": "Quillan Salkilld",
        "odds": "-215",
        "numericOdds": -215
      },
      "isLocked": false,
      "extractionId": 52
    },
    {
      "timestamp": "2026-05-02T13:21:18.853Z",
      "fighter1": {
        "name": "Beneil Dariush",
        "odds": "+330",
        "numericOdds": 330
      },
      "fighter2": {
        "name": "Quillan Salkilld",
        "odds": "-480",
        "numericOdds": -480
      },
      "isLocked": false,
      "extractionId": 35
    },
    {
      "timestamp": "2026-05-02T13:21:21.856Z",
      "fighter1": {
        "name": "Beneil Dariush",
        "odds": "+330",
        "numericOdds": 330
      },
      "fighter2": {
        "name": "Quillan Salkilld",
        "odds": "-480",
        "numericOdds": -480
      },
      "isLocked": false,
      "extractionId": 2
    },
    {
      "timestamp": "2026-05-02T13:21:24.861Z",
      "fighter1": {
        "name": "Beneil Dariush",
        "odds": "+270",
        "numericOdds": 270
      },
      "fighter2": {
        "name": "Quillan Salkilld",
        "odds": "-380",
        "numericOdds": -380
      },
      "isLocked": false,
      "extractionId": 3
    },
    {
      "timestamp": "2026-05-02T13:21:27.876Z",
      "fighter1": {
        "name": "Beneil Dariush",
        "odds": "+270",
        "numericOdds": 270
      },
      "fighter2": {
        "name": "Quillan Salkilld",
        "odds": "-380",
        "numericOdds": -380
      },
      "isLocked": false,
      "extractionId": 4
    },
    {
      "timestamp": "2026-05-02T13:21:30.880Z",
      "fighter1": {
        "name": "Beneil Dariush",
        "odds": "+225",
        "numericOdds": 225
      },
      "fighter2": {
        "name": "Quillan Salkilld",
        "odds": "-310",
        "numericOdds": -310
      },
      "isLocked": false,
      "extractionId": 5
    },
    {
      "timestamp": "2026-05-02T13:21:33.883Z",
      "fighter1": {
        "name": "Beneil Dariush",
        "odds": "+184",
        "numericOdds": 184
      },
      "fighter2": {
        "name": "Quillan Salkilld",
        "odds": "-240",
        "numericOdds": -240
      },
      "isLocked": false,
      "extractionId": 6
    },
    {
      "timestamp": "2026-05-02T13:21:36.892Z",
      "fighter1": {
        "name": "Beneil Dariush",
        "odds": "+184",
        "numericOdds": 184
      },
      "fighter2": {
        "name": "Quillan Salkilld",
        "odds": "-240",
        "numericOdds": -240
      },
      "isLocked": false,
      "extractionId": 7
    },
    {
      "timestamp": "2026-05-02T13:21:39.895Z",
      "fighter1": {
        "name": "Beneil Dariush",
        "odds": "+158",
        "numericOdds": 158
      },
      "fighter2": {
        "name": "Quillan Salkilld",
        "odds": "-205",
        "numericOdds": -205
      },
      "isLocked": false,
      "extractionId": 8
    },
    {
      "timestamp": "2026-05-02T13:21:42.907Z",
      "fighter1": {
        "name": "Beneil Dariush",
        "odds": "+158",
        "numericOdds": 158
      },
      "fighter2": {
        "name": "Quillan Salkilld",
        "odds": "-205",
        "numericOdds": -205
      },
      "isLocked": false,
      "extractionId": 9
    },
    {
      "timestamp": "2026-05-02T13:21:45.915Z",
      "fighter1": {
        "name": "Beneil Dariush",
        "odds": "+158",
        "numericOdds": 158
      },
      "fighter2": {
        "name": "Quillan Salkilld",
        "odds": "-205",
        "numericOdds": -205
      },
      "isLocked": false,
      "extractionId": 10
    },
    {
      "timestamp": "2026-05-02T13:21:48.926Z",
      "fighter1": {
        "name": "Beneil Dariush",
        "odds": "+158",
        "numericOdds": 158
      },
      "fighter2": {
        "name": "Quillan Salkilld",
        "odds": "-205",
        "numericOdds": -205
      },
      "isLocked": false,
      "extractionId": 11
    },
    {
      "timestamp": "2026-05-02T13:21:51.937Z",
      "fighter1": {
        "name": "Beneil Dariush",
        "odds": "+158",
        "numericOdds": 158
      },
      "fighter2": {
        "name": "Quillan Salkilld",
        "odds": "-205",
        "numericOdds": -205
      },
      "isLocked": false,
      "extractionId": 12
    },
    {
      "timestamp": "2026-05-02T13:21:54.945Z",
      "fighter1": {
        "name": "Beneil Dariush",
        "odds": "+158",
        "numericOdds": 158
      },
      "fighter2": {
        "name": "Quillan Salkilld",
        "odds": "-205",
        "numericOdds": -205
      },
      "isLocked": false,
      "extractionId": 13
    },
    {
      "timestamp": "2026-05-02T13:21:57.950Z",
      "fighter1": {
        "name": "Beneil Dariush",
        "odds": "+158",
        "numericOdds": 158
      },
      "fighter2": {
        "name": "Quillan Salkilld",
        "odds": "-205",
        "numericOdds": -205
      },
      "isLocked": false,
      "extractionId": 14
    },
    {
      "timestamp": "2026-05-02T13:22:00.960Z",
      "fighter1": {
        "name": "Beneil Dariush",
        "odds": "+172",
        "numericOdds": 172
      },
      "fighter2": {
        "name": "Quillan Salkilld",
        "odds": "-225",
        "numericOdds": -225
      },
      "isLocked": false,
      "extractionId": 15
    },
    {
      "timestamp": "2026-05-02T13:22:03.960Z",
      "fighter1": {
        "name": "Beneil Dariush",
        "odds": "+172",
        "numericOdds": 172
      },
      "fighter2": {
        "name": "Quillan Salkilld",
        "odds": "-225",
        "numericOdds": -225
      },
      "isLocked": false,
      "extractionId": 16
    },
    {
      "timestamp": "2026-05-02T13:22:06.969Z",
      "fighter1": {
        "name": "Beneil Dariush",
        "odds": "+172",
        "numericOdds": 172
      },
      "fighter2": {
        "name": "Quillan Salkilld",
        "odds": "-225",
        "numericOdds": -225
      },
      "isLocked": false,
      "extractionId": 17
    },
    {
      "timestamp": "2026-05-02T13:22:09.974Z",
      "fighter1": {
        "name": "Beneil Dariush",
        "odds": "+152",
        "numericOdds": 152
      },
      "fighter2": {
        "name": "Quillan Salkilld",
        "odds": "-196",
        "numericOdds": -196
      },
      "isLocked": false,
      "extractionId": 18
    },
    {
      "timestamp": "2026-05-02T13:22:12.982Z",
      "fighter1": {
        "name": "Beneil Dariush",
        "odds": "+152",
        "numericOdds": 152
      },
      "fighter2": {
        "name": "Quillan Salkilld",
        "odds": "-196",
        "numericOdds": -196
      },
      "isLocked": false,
      "extractionId": 19
    },
    {
      "timestamp": "2026-05-02T13:22:15.985Z",
      "fighter1": {
        "name": "Beneil Dariush",
        "odds": "+152",
        "numericOdds": 152
      },
      "fighter2": {
        "name": "Quillan Salkilld",
        "odds": "-196",
        "numericOdds": -196
      },
      "isLocked": false,
      "extractionId": 20
    },
    {
      "timestamp": "2026-05-02T13:22:18.992Z",
      "fighter1": {
        "name": "Beneil Dariush",
        "odds": "+152",
        "numericOdds": 152
      },
      "fighter2": {
        "name": "Quillan Salkilld",
        "odds": "-196",
        "numericOdds": -196
      },
      "isLocked": false,
      "extractionId": 21
    },
    {
      "timestamp": "2026-05-02T13:22:21.999Z",
      "fighter1": {
        "name": "Beneil Dariush",
        "odds": "+152",
        "numericOdds": 152
      },
      "fighter2": {
        "name": "Quillan Salkilld",
        "odds": "-196",
        "numericOdds": -196
      },
      "isLocked": false,
      "extractionId": 22
    },
    {
      "timestamp": "2026-05-02T13:22:25.007Z",
      "fighter1": {
        "name": "Beneil Dariush",
        "odds": "+152",
        "numericOdds": 152
      },
      "fighter2": {
        "name": "Quillan Salkilld",
        "odds": "-196",
        "numericOdds": -196
      },
      "isLocked": false,
      "extractionId": 23
    },
    {
      "timestamp": "2026-05-02T13:22:28.012Z",
      "fighter1": {
        "name": "Beneil Dariush",
        "odds": "+152",
        "numericOdds": 152
      },
      "fighter2": {
        "name": "Quillan Salkilld",
        "odds": "-196",
        "numericOdds": -196
      },
      "isLocked": false,
      "extractionId": 24
    },
    {
      "timestamp": "2026-05-02T13:22:31.020Z",
      "fighter1": {
        "name": "Beneil Dariush",
        "odds": "+152",
        "numericOdds": 152
      },
      "fighter2": {
        "name": "Quillan Salkilld",
        "odds": "-196",
        "numericOdds": -196
      },
      "isLocked": false,
      "extractionId": 25
    },
    {
      "timestamp": "2026-05-02T13:22:34.027Z",
      "fighter1": {
        "name": "Beneil Dariush",
        "odds": "+158",
        "numericOdds": 158
      },
      "fighter2": {
        "name": "Quillan Salkilld",
        "odds": "-205",
        "numericOdds": -205
      },
      "isLocked": false,
      "extractionId": 26
    },
    {
      "timestamp": "2026-05-02T13:22:37.034Z",
      "fighter1": {
        "name": "Beneil Dariush",
        "odds": "+158",
        "numericOdds": 158
      },
      "fighter2": {
        "name": "Quillan Salkilld",
        "odds": "-205",
        "numericOdds": -205
      },
      "isLocked": false,
      "extractionId": 27
    },
    {
      "timestamp": "2026-05-02T13:22:40.035Z",
      "fighter1": {
        "name": "Beneil Dariush",
        "odds": "+158",
        "numericOdds": 158
      },
      "fighter2": {
        "name": "Quillan Salkilld",
        "odds": "-205",
        "numericOdds": -205
      },
      "isLocked": false,
      "extractionId": 28
    },
    {
      "timestamp": "2026-05-02T13:22:43.045Z",
      "fighter1": {
        "name": "Beneil Dariush",
        "odds": "+158",
        "numericOdds": 158
      },
      "fighter2": {
        "name": "Quillan Salkilld",
        "odds": "-205",
        "numericOdds": -205
      },
      "isLocked": false,
      "extractionId": 29
    },
    {
      "timestamp": "2026-05-02T13:22:46.053Z",
      "fighter1": {
        "name": "Beneil Dariush",
        "odds": "+158",
        "numericOdds": 158
      },
      "fighter2": {
        "name": "Quillan Salkilld",
        "odds": "-205",
        "numericOdds": -205
      },
      "isLocked": false,
      "extractionId": 30
    },
    {
      "timestamp": "2026-05-02T13:22:49.054Z",
      "fighter1": {
        "name": "Beneil Dariush",
        "odds": "+158",
        "numericOdds": 158
      },
      "fighter2": {
        "name": "Quillan Salkilld",
        "odds": "-205",
        "numericOdds": -205
      },
      "isLocked": false,
      "extractionId": 31
    },
    {
      "timestamp": "2026-05-02T13:22:52.068Z",
      "fighter1": {
        "name": "Beneil Dariush",
        "odds": "+158",
        "numericOdds": 158
      },
      "fighter2": {
        "name": "Quillan Salkilld",
        "odds": "-205",
        "numericOdds": -205
      },
      "isLocked": false,
      "extractionId": 32
    },
    {
      "timestamp": "2026-05-02T13:22:55.080Z",
      "fighter1": {
        "name": "Beneil Dariush",
        "odds": "+160",
        "numericOdds": 160
      },
      "fighter2": {
        "name": "Quillan Salkilld",
        "odds": "-210",
        "numericOdds": -210
      },
      "isLocked": false,
      "extractionId": 33
    },
    {
      "timestamp": "2026-05-02T13:22:58.084Z",
      "fighter1": {
        "name": "Beneil Dariush",
        "odds": "+160",
        "numericOdds": 160
      },
      "fighter2": {
        "name": "Quillan Salkilld",
        "odds": "-210",
        "numericOdds": -210
      },
      "isLocked": false,
      "extractionId": 34
    },
    {
      "timestamp": "2026-05-02T13:23:01.098Z",
      "fighter1": {
        "name": "Beneil Dariush",
        "odds": "+164",
        "numericOdds": 164
      },
      "fighter2": {
        "name": "Quillan Salkilld",
        "odds": "-215",
        "numericOdds": -215
      },
      "isLocked": false,
      "extractionId": 35
    },
    {
      "timestamp": "2026-05-02T13:23:04.100Z",
      "fighter1": {
        "name": "Beneil Dariush",
        "odds": "+164",
        "numericOdds": 164
      },
      "fighter2": {
        "name": "Quillan Salkilld",
        "odds": "-215",
        "numericOdds": -215
      },
      "isLocked": false,
      "extractionId": 36
    },
    {
      "timestamp": "2026-05-02T13:23:07.112Z",
      "fighter1": {
        "name": "Beneil Dariush",
        "odds": "+164",
        "numericOdds": 164
      },
      "fighter2": {
        "name": "Quillan Salkilld",
        "odds": "-215",
        "numericOdds": -215
      },
      "isLocked": false,
      "extractionId": 37
    },
    {
      "timestamp": "2026-05-02T13:23:10.122Z",
      "fighter1": {
        "name": "Beneil Dariush",
        "odds": "+164",
        "numericOdds": 164
      },
      "fighter2": {
        "name": "Quillan Salkilld",
        "odds": "-215",
        "numericOdds": -215
      },
      "isLocked": false,
      "extractionId": 38
    },
    {
      "timestamp": "2026-05-02T13:23:13.126Z",
      "fighter1": {
        "name": "Beneil Dariush",
        "odds": "+164",
        "numericOdds": 164
      },
      "fighter2": {
        "name": "Quillan Salkilld",
        "odds": "-215",
        "numericOdds": -215
      },
      "isLocked": false,
      "extractionId": 39
    },
    {
      "timestamp": "2026-05-02T13:23:16.134Z",
      "fighter1": {
        "name": "Beneil Dariush",
        "odds": "+164",
        "numericOdds": 164
      },
      "fighter2": {
        "name": "Quillan Salkilld",
        "odds": "-215",
        "numericOdds": -215
      },
      "isLocked": false,
      "extractionId": 40
    },
    {
      "timestamp": "2026-05-02T13:23:19.134Z",
      "fighter1": {
        "name": "Beneil Dariush",
        "odds": "+164",
        "numericOdds": 164
      },
      "fighter2": {
        "name": "Quillan Salkilld",
        "odds": "-215",
        "numericOdds": -215
      },
      "isLocked": false,
      "extractionId": 41
    },
    {
      "timestamp": "2026-05-02T13:23:22.145Z",
      "fighter1": {
        "name": "Beneil Dariush",
        "odds": "+164",
        "numericOdds": 164
      },
      "fighter2": {
        "name": "Quillan Salkilld",
        "odds": "-215",
        "numericOdds": -215
      },
      "isLocked": false,
      "extractionId": 42
    },
    {
      "timestamp": "2026-05-02T13:23:25.158Z",
      "fighter1": {
        "name": "Beneil Dariush",
        "odds": "+164",
        "numericOdds": 164
      },
      "fighter2": {
        "name": "Quillan Salkilld",
        "odds": "-215",
        "numericOdds": -215
      },
      "isLocked": false,
      "extractionId": 43
    },
    {
      "timestamp": "2026-05-02T13:23:28.165Z",
      "fighter1": {
        "name": "Beneil Dariush",
        "odds": "+164",
        "numericOdds": 164
      },
      "fighter2": {
        "name": "Quillan Salkilld",
        "odds": "-215",
        "numericOdds": -215
      },
      "isLocked": false,
      "extractionId": 44
    },
    {
      "timestamp": "2026-05-02T13:23:31.166Z",
      "fighter1": {
        "name": "Beneil Dariush",
        "odds": "+164",
        "numericOdds": 164
      },
      "fighter2": {
        "name": "Quillan Salkilld",
        "odds": "-215",
        "numericOdds": -215
      },
      "isLocked": false,
      "extractionId": 45
    },
    {
      "timestamp": "2026-05-02T13:23:34.170Z",
      "fighter1": {
        "name": "Beneil Dariush",
        "odds": "+164",
        "numericOdds": 164
      },
      "fighter2": {
        "name": "Quillan Salkilld",
        "odds": "-215",
        "numericOdds": -215
      },
      "isLocked": false,
      "extractionId": 46
    },
    {
      "timestamp": "2026-05-02T13:23:37.183Z",
      "fighter1": {
        "name": "Beneil Dariush",
        "odds": "+164",
        "numericOdds": 164
      },
      "fighter2": {
        "name": "Quillan Salkilld",
        "odds": "-215",
        "numericOdds": -215
      },
      "isLocked": false,
      "extractionId": 47
    },
    {
      "timestamp": "2026-05-02T13:23:40.191Z",
      "fighter1": {
        "name": "Beneil Dariush",
        "odds": "+164",
        "numericOdds": 164
      },
      "fighter2": {
        "name": "Quillan Salkilld",
        "odds": "-215",
        "numericOdds": -215
      },
      "isLocked": false,
      "extractionId": 48
    },
    {
      "timestamp": "2026-05-02T13:23:43.193Z",
      "fighter1": {
        "name": "Beneil Dariush",
        "odds": "+164",
        "numericOdds": 164
      },
      "fighter2": {
        "name": "Quillan Salkilld",
        "odds": "-215",
        "numericOdds": -215
      },
      "isLocked": false,
      "extractionId": 49
    },
    {
      "timestamp": "2026-05-02T13:23:46.203Z",
      "fighter1": {
        "name": "Beneil Dariush",
        "odds": "+166",
        "numericOdds": 166
      },
      "fighter2": {
        "name": "Quillan Salkilld",
        "odds": "-215",
        "numericOdds": -215
      },
      "isLocked": false,
      "extractionId": 50
    },
    {
      "timestamp": "2026-05-02T13:23:49.208Z",
      "fighter1": {
        "name": "Beneil Dariush",
        "odds": "+166",
        "numericOdds": 166
      },
      "fighter2": {
        "name": "Quillan Salkilld",
        "odds": "-215",
        "numericOdds": -215
      },
      "isLocked": false,
      "extractionId": 51
    },
    {
      "timestamp": "2026-05-02T13:23:52.220Z",
      "fighter1": {
        "name": "Beneil Dariush",
        "odds": "+166",
        "numericOdds": 166
      },
      "fighter2": {
        "name": "Quillan Salkilld",
        "odds": "-215",
        "numericOdds": -215
      },
      "isLocked": false,
      "extractionId": 52
    }
  ]
}