{
  "fightId": "clayguida_vs_markomadsen_2021-08-22",
  "fightTitle": "Clay Guida vs Mark O. Madsen",
  "commenceTime": null,
  "startTime": "2021-08-22T04:15:00Z",
  "endTime": "2021-08-22T04:45:00Z",
  "dataPoints": 4,
  "oddsHistory": [
    {
      "timestamp": "2021-08-22T04:15:00Z",
      "fighter1": {
        "name": "Clay Guida",
        "numericOdds": 150
      },
      "fighter2": {
        "name": "Mark O. Madsen",
        "numericOdds": -169
      }
    },
    {
      "timestamp": "2021-08-22T04:25:00Z",
      "fighter1": {
        "name": "Clay Guida",
        "numericOdds": 145
      },
      "fighter2": {
        "name": "Mark O. Madsen",
        "numericOdds": -196
      }
    },
    {
      "timestamp": "2021-08-22T04:35:00Z",
      "fighter1": {
        "name": "Clay Guida",
        "numericOdds": -189
      },
      "fighter2": {
        "name": "Mark O. Madsen",
        "numericOdds": 140
      }
    },
    {
      "timestamp": "2021-08-22T04:45:00Z",
      "fighter1": {
        "name": "Clay Guida",
        "numericOdds": -135
      },
      "fighter2": {
        "name": "Mark O. Madsen",
        "numericOdds": 100
      }
    }
  ]
}