{
  "fightId": "elvesbrenner_vs_joelalvarez_2024-08-03",
  "fightTitle": "Elves Brenner vs Joel Alvarez",
  "startTime": "2024-08-03T13:55:38Z",
  "endTime": "2024-08-03T19:30:37Z",
  "dataPoints": 25,
  "oddsHistory": [
    {
      "timestamp": "2024-08-03T13:55:38Z",
      "fighter1": {
        "name": "Elves Brenner",
        "numericOdds": 130
      },
      "fighter2": {
        "name": "Joel Alvarez",
        "numericOdds": -155
      }
    },
    {
      "timestamp": "2024-08-03T14:10:38Z",
      "fighter1": {
        "name": "Elves Brenner",
        "numericOdds": 130
      },
      "fighter2": {
        "name": "Joel Alvarez",
        "numericOdds": -155
      }
    },
    {
      "timestamp": "2024-08-03T14:25:38Z",
      "fighter1": {
        "name": "Elves Brenner",
        "numericOdds": 130
      },
      "fighter2": {
        "name": "Joel Alvarez",
        "numericOdds": -155
      }
    },
    {
      "timestamp": "2024-08-03T14:40:38Z",
      "fighter1": {
        "name": "Elves Brenner",
        "numericOdds": 130
      },
      "fighter2": {
        "name": "Joel Alvarez",
        "numericOdds": -155
      }
    },
    {
      "timestamp": "2024-08-03T14:55:38Z",
      "fighter1": {
        "name": "Elves Brenner",
        "numericOdds": 124
      },
      "fighter2": {
        "name": "Joel Alvarez",
        "numericOdds": -148
      }
    },
    {
      "timestamp": "2024-08-03T15:10:38Z",
      "fighter1": {
        "name": "Elves Brenner",
        "numericOdds": 124
      },
      "fighter2": {
        "name": "Joel Alvarez",
        "numericOdds": -148
      }
    },
    {
      "timestamp": "2024-08-03T15:25:38Z",
      "fighter1": {
        "name": "Elves Brenner",
        "numericOdds": 124
      },
      "fighter2": {
        "name": "Joel Alvarez",
        "numericOdds": -148
      }
    },
    {
      "timestamp": "2024-08-03T15:40:38Z",
      "fighter1": {
        "name": "Elves Brenner",
        "numericOdds": 124
      },
      "fighter2": {
        "name": "Joel Alvarez",
        "numericOdds": -148
      }
    },
    {
      "timestamp": "2024-08-03T15:55:38Z",
      "fighter1": {
        "name": "Elves Brenner",
        "numericOdds": 124
      },
      "fighter2": {
        "name": "Joel Alvarez",
        "numericOdds": -148
      }
    },
    {
      "timestamp": "2024-08-03T16:10:38Z",
      "fighter1": {
        "name": "Elves Brenner",
        "numericOdds": 124
      },
      "fighter2": {
        "name": "Joel Alvarez",
        "numericOdds": -148
      }
    },
    {
      "timestamp": "2024-08-03T16:25:38Z",
      "fighter1": {
        "name": "Elves Brenner",
        "numericOdds": 124
      },
      "fighter2": {
        "name": "Joel Alvarez",
        "numericOdds": -155
      }
    },
    {
      "timestamp": "2024-08-03T16:40:37Z",
      "fighter1": {
        "name": "Elves Brenner",
        "numericOdds": 136
      },
      "fighter2": {
        "name": "Joel Alvarez",
        "numericOdds": -162
      }
    },
    {
      "timestamp": "2024-08-03T16:50:38Z",
      "fighter1": {
        "name": "Elves Brenner",
        "numericOdds": 136
      },
      "fighter2": {
        "name": "Joel Alvarez",
        "numericOdds": -162
      }
    },
    {
      "timestamp": "2024-08-03T17:05:37Z",
      "fighter1": {
        "name": "Elves Brenner",
        "numericOdds": 136
      },
      "fighter2": {
        "name": "Joel Alvarez",
        "numericOdds": -162
      }
    },
    {
      "timestamp": "2024-08-03T17:20:37Z",
      "fighter1": {
        "name": "Elves Brenner",
        "numericOdds": 136
      },
      "fighter2": {
        "name": "Joel Alvarez",
        "numericOdds": -162
      }
    },
    {
      "timestamp": "2024-08-03T17:30:38Z",
      "fighter1": {
        "name": "Elves Brenner",
        "numericOdds": 136
      },
      "fighter2": {
        "name": "Joel Alvarez",
        "numericOdds": -162
      }
    },
    {
      "timestamp": "2024-08-03T17:45:38Z",
      "fighter1": {
        "name": "Elves Brenner",
        "numericOdds": 136
      },
      "fighter2": {
        "name": "Joel Alvarez",
        "numericOdds": -162
      }
    },
    {
      "timestamp": "2024-08-03T17:55:38Z",
      "fighter1": {
        "name": "Elves Brenner",
        "numericOdds": 136
      },
      "fighter2": {
        "name": "Joel Alvarez",
        "numericOdds": -162
      }
    },
    {
      "timestamp": "2024-08-03T18:10:38Z",
      "fighter1": {
        "name": "Elves Brenner",
        "numericOdds": 136
      },
      "fighter2": {
        "name": "Joel Alvarez",
        "numericOdds": -162
      }
    },
    {
      "timestamp": "2024-08-03T18:25:38Z",
      "fighter1": {
        "name": "Elves Brenner",
        "numericOdds": 136
      },
      "fighter2": {
        "name": "Joel Alvarez",
        "numericOdds": -162
      }
    },
    {
      "timestamp": "2024-08-03T18:40:37Z",
      "fighter1": {
        "name": "Elves Brenner",
        "numericOdds": 136
      },
      "fighter2": {
        "name": "Joel Alvarez",
        "numericOdds": -162
      }
    },
    {
      "timestamp": "2024-08-03T18:55:37Z",
      "fighter1": {
        "name": "Elves Brenner",
        "numericOdds": 140
      },
      "fighter2": {
        "name": "Joel Alvarez",
        "numericOdds": -166
      }
    },
    {
      "timestamp": "2024-08-03T19:10:37Z",
      "fighter1": {
        "name": "Elves Brenner",
        "numericOdds": 200
      },
      "fighter2": {
        "name": "Joel Alvarez",
        "numericOdds": -270
      }
    },
    {
      "timestamp": "2024-08-03T19:20:37Z",
      "fighter1": {
        "name": "Elves Brenner",
        "numericOdds": 750
      },
      "fighter2": {
        "name": "Joel Alvarez",
        "numericOdds": -1450
      }
    },
    {
      "timestamp": "2024-08-03T19:30:37Z",
      "fighter1": {
        "name": "Elves Brenner",
        "numericOdds": 1200
      },
      "fighter2": {
        "name": "Joel Alvarez",
        "numericOdds": -2800
      }
    }
  ]
}