{
  "fightId": "evanelder_vs_genarovaldez_2023-07-16",
  "fightTitle": "Evan Elder vs Genaro Valdez",
  "commenceTime": null,
  "startTime": "2023-07-16T00:15:39Z",
  "endTime": "2023-07-16T01:00:40Z",
  "dataPoints": 5,
  "oddsHistory": [
    {
      "timestamp": "2023-07-16T00:15:39Z",
      "fighter1": {
        "name": "Evan Elder",
        "numericOdds": -295
      },
      "fighter2": {
        "name": "Genaro Valdez",
        "numericOdds": 245
      }
    },
    {
      "timestamp": "2023-07-16T00:25:39Z",
      "fighter1": {
        "name": "Evan Elder",
        "numericOdds": -295
      },
      "fighter2": {
        "name": "Genaro Valdez",
        "numericOdds": 245
      }
    },
    {
      "timestamp": "2023-07-16T00:35:39Z",
      "fighter1": {
        "name": "Evan Elder",
        "numericOdds": -550
      },
      "fighter2": {
        "name": "Genaro Valdez",
        "numericOdds": 400
      }
    },
    {
      "timestamp": "2023-07-16T00:50:39Z",
      "fighter1": {
        "name": "Evan Elder",
        "numericOdds": -750
      },
      "fighter2": {
        "name": "Genaro Valdez",
        "numericOdds": 500
      }
    },
    {
      "timestamp": "2023-07-16T01:00:40Z",
      "fighter1": {
        "name": "Evan Elder",
        "numericOdds": -1450
      },
      "fighter2": {
        "name": "Genaro Valdez",
        "numericOdds": 800
      }
    }
  ]
}