{
  "fightId": "nazimsadykhov_vs_faresziam_2025-12-07",
  "fightTitle": "Nazim Sadykhov vs Fares Ziam",
  "commenceTime": null,
  "startTime": "2025-12-07T00:55:37Z",
  "endTime": "2025-12-07T01:25:37Z",
  "dataPoints": 3,
  "oddsHistory": [
    {
      "timestamp": "2025-12-07T00:55:37Z",
      "fighter1": {
        "name": "Fares Ziam",
        "numericOdds": -192
      },
      "fighter2": {
        "name": "Nazim Sadykhov",
        "numericOdds": 160
      }
    },
    {
      "timestamp": "2025-12-07T01:10:37Z",
      "fighter1": {
        "name": "Fares Ziam",
        "numericOdds": -192
      },
      "fighter2": {
        "name": "Nazim Sadykhov",
        "numericOdds": 160
      }
    },
    {
      "timestamp": "2025-12-07T01:25:37Z",
      "fighter1": {
        "name": "Fares Ziam",
        "numericOdds": -2100
      },
      "fighter2": {
        "name": "Nazim Sadykhov",
        "numericOdds": 1000
      }
    }
  ]
}