{
  "fightId": "sijaraeubanks_vs_elisereed_2021-07-24",
  "fightTitle": "Sijara Eubanks vs Elise Reed",
  "commenceTime": null,
  "startTime": "2021-07-24T00:45:00Z",
  "endTime": "2021-07-24T21:05:00Z",
  "dataPoints": 123,
  "oddsHistory": [
    {
      "timestamp": "2021-07-24T00:45:00Z",
      "fighter1": {
        "name": "Elise Reed",
        "numericOdds": 290
      },
      "fighter2": {
        "name": "Sijara Eubanks",
        "numericOdds": -385
      }
    },
    {
      "timestamp": "2021-07-24T00:55:00Z",
      "fighter1": {
        "name": "Elise Reed",
        "numericOdds": 290
      },
      "fighter2": {
        "name": "Sijara Eubanks",
        "numericOdds": -385
      }
    },
    {
      "timestamp": "2021-07-24T01:05:00Z",
      "fighter1": {
        "name": "Elise Reed",
        "numericOdds": 300
      },
      "fighter2": {
        "name": "Sijara Eubanks",
        "numericOdds": -400
      }
    },
    {
      "timestamp": "2021-07-24T01:15:00Z",
      "fighter1": {
        "name": "Elise Reed",
        "numericOdds": 300
      },
      "fighter2": {
        "name": "Sijara Eubanks",
        "numericOdds": -400
      }
    },
    {
      "timestamp": "2021-07-24T01:25:00Z",
      "fighter1": {
        "name": "Elise Reed",
        "numericOdds": 300
      },
      "fighter2": {
        "name": "Sijara Eubanks",
        "numericOdds": -400
      }
    },
    {
      "timestamp": "2021-07-24T01:35:00Z",
      "fighter1": {
        "name": "Elise Reed",
        "numericOdds": 300
      },
      "fighter2": {
        "name": "Sijara Eubanks",
        "numericOdds": -400
      }
    },
    {
      "timestamp": "2021-07-24T01:45:00Z",
      "fighter1": {
        "name": "Elise Reed",
        "numericOdds": 300
      },
      "fighter2": {
        "name": "Sijara Eubanks",
        "numericOdds": -400
      }
    },
    {
      "timestamp": "2021-07-24T01:55:00Z",
      "fighter1": {
        "name": "Elise Reed",
        "numericOdds": 300
      },
      "fighter2": {
        "name": "Sijara Eubanks",
        "numericOdds": -400
      }
    },
    {
      "timestamp": "2021-07-24T02:05:00Z",
      "fighter1": {
        "name": "Elise Reed",
        "numericOdds": 300
      },
      "fighter2": {
        "name": "Sijara Eubanks",
        "numericOdds": -400
      }
    },
    {
      "timestamp": "2021-07-24T02:15:00Z",
      "fighter1": {
        "name": "Elise Reed",
        "numericOdds": 300
      },
      "fighter2": {
        "name": "Sijara Eubanks",
        "numericOdds": -400
      }
    },
    {
      "timestamp": "2021-07-24T02:25:00Z",
      "fighter1": {
        "name": "Elise Reed",
        "numericOdds": 300
      },
      "fighter2": {
        "name": "Sijara Eubanks",
        "numericOdds": -400
      }
    },
    {
      "timestamp": "2021-07-24T02:35:00Z",
      "fighter1": {
        "name": "Elise Reed",
        "numericOdds": 300
      },
      "fighter2": {
        "name": "Sijara Eubanks",
        "numericOdds": -400
      }
    },
    {
      "timestamp": "2021-07-24T02:45:00Z",
      "fighter1": {
        "name": "Elise Reed",
        "numericOdds": 300
      },
      "fighter2": {
        "name": "Sijara Eubanks",
        "numericOdds": -400
      }
    },
    {
      "timestamp": "2021-07-24T02:55:00Z",
      "fighter1": {
        "name": "Elise Reed",
        "numericOdds": 300
      },
      "fighter2": {
        "name": "Sijara Eubanks",
        "numericOdds": -400
      }
    },
    {
      "timestamp": "2021-07-24T03:05:00Z",
      "fighter1": {
        "name": "Elise Reed",
        "numericOdds": 300
      },
      "fighter2": {
        "name": "Sijara Eubanks",
        "numericOdds": -400
      }
    },
    {
      "timestamp": "2021-07-24T03:15:00Z",
      "fighter1": {
        "name": "Elise Reed",
        "numericOdds": 300
      },
      "fighter2": {
        "name": "Sijara Eubanks",
        "numericOdds": -400
      }
    },
    {
      "timestamp": "2021-07-24T03:25:00Z",
      "fighter1": {
        "name": "Elise Reed",
        "numericOdds": 300
      },
      "fighter2": {
        "name": "Sijara Eubanks",
        "numericOdds": -400
      }
    },
    {
      "timestamp": "2021-07-24T03:35:00Z",
      "fighter1": {
        "name": "Elise Reed",
        "numericOdds": 300
      },
      "fighter2": {
        "name": "Sijara Eubanks",
        "numericOdds": -400
      }
    },
    {
      "timestamp": "2021-07-24T03:45:00Z",
      "fighter1": {
        "name": "Elise Reed",
        "numericOdds": 300
      },
      "fighter2": {
        "name": "Sijara Eubanks",
        "numericOdds": -400
      }
    },
    {
      "timestamp": "2021-07-24T03:55:00Z",
      "fighter1": {
        "name": "Elise Reed",
        "numericOdds": 300
      },
      "fighter2": {
        "name": "Sijara Eubanks",
        "numericOdds": -400
      }
    },
    {
      "timestamp": "2021-07-24T04:05:00Z",
      "fighter1": {
        "name": "Elise Reed",
        "numericOdds": 300
      },
      "fighter2": {
        "name": "Sijara Eubanks",
        "numericOdds": -400
      }
    },
    {
      "timestamp": "2021-07-24T04:15:00Z",
      "fighter1": {
        "name": "Elise Reed",
        "numericOdds": 300
      },
      "fighter2": {
        "name": "Sijara Eubanks",
        "numericOdds": -400
      }
    },
    {
      "timestamp": "2021-07-24T04:25:00Z",
      "fighter1": {
        "name": "Elise Reed",
        "numericOdds": 300
      },
      "fighter2": {
        "name": "Sijara Eubanks",
        "numericOdds": -400
      }
    },
    {
      "timestamp": "2021-07-24T04:35:00Z",
      "fighter1": {
        "name": "Elise Reed",
        "numericOdds": 300
      },
      "fighter2": {
        "name": "Sijara Eubanks",
        "numericOdds": -400
      }
    },
    {
      "timestamp": "2021-07-24T04:45:00Z",
      "fighter1": {
        "name": "Elise Reed",
        "numericOdds": 300
      },
      "fighter2": {
        "name": "Sijara Eubanks",
        "numericOdds": -400
      }
    },
    {
      "timestamp": "2021-07-24T04:55:00Z",
      "fighter1": {
        "name": "Elise Reed",
        "numericOdds": 300
      },
      "fighter2": {
        "name": "Sijara Eubanks",
        "numericOdds": -400
      }
    },
    {
      "timestamp": "2021-07-24T05:05:00Z",
      "fighter1": {
        "name": "Elise Reed",
        "numericOdds": 290
      },
      "fighter2": {
        "name": "Sijara Eubanks",
        "numericOdds": -385
      }
    },
    {
      "timestamp": "2021-07-24T05:15:00Z",
      "fighter1": {
        "name": "Elise Reed",
        "numericOdds": 290
      },
      "fighter2": {
        "name": "Sijara Eubanks",
        "numericOdds": -385
      }
    },
    {
      "timestamp": "2021-07-24T05:25:00Z",
      "fighter1": {
        "name": "Elise Reed",
        "numericOdds": 290
      },
      "fighter2": {
        "name": "Sijara Eubanks",
        "numericOdds": -385
      }
    },
    {
      "timestamp": "2021-07-24T05:35:00Z",
      "fighter1": {
        "name": "Elise Reed",
        "numericOdds": 290
      },
      "fighter2": {
        "name": "Sijara Eubanks",
        "numericOdds": -385
      }
    },
    {
      "timestamp": "2021-07-24T05:45:00Z",
      "fighter1": {
        "name": "Elise Reed",
        "numericOdds": 290
      },
      "fighter2": {
        "name": "Sijara Eubanks",
        "numericOdds": -385
      }
    },
    {
      "timestamp": "2021-07-24T05:55:00Z",
      "fighter1": {
        "name": "Elise Reed",
        "numericOdds": 290
      },
      "fighter2": {
        "name": "Sijara Eubanks",
        "numericOdds": -385
      }
    },
    {
      "timestamp": "2021-07-24T06:05:00Z",
      "fighter1": {
        "name": "Elise Reed",
        "numericOdds": 300
      },
      "fighter2": {
        "name": "Sijara Eubanks",
        "numericOdds": -400
      }
    },
    {
      "timestamp": "2021-07-24T06:15:00Z",
      "fighter1": {
        "name": "Elise Reed",
        "numericOdds": 300
      },
      "fighter2": {
        "name": "Sijara Eubanks",
        "numericOdds": -400
      }
    },
    {
      "timestamp": "2021-07-24T06:25:00Z",
      "fighter1": {
        "name": "Elise Reed",
        "numericOdds": 300
      },
      "fighter2": {
        "name": "Sijara Eubanks",
        "numericOdds": -400
      }
    },
    {
      "timestamp": "2021-07-24T06:35:00Z",
      "fighter1": {
        "name": "Elise Reed",
        "numericOdds": 300
      },
      "fighter2": {
        "name": "Sijara Eubanks",
        "numericOdds": -400
      }
    },
    {
      "timestamp": "2021-07-24T06:45:00Z",
      "fighter1": {
        "name": "Elise Reed",
        "numericOdds": 300
      },
      "fighter2": {
        "name": "Sijara Eubanks",
        "numericOdds": -400
      }
    },
    {
      "timestamp": "2021-07-24T06:55:00Z",
      "fighter1": {
        "name": "Elise Reed",
        "numericOdds": 300
      },
      "fighter2": {
        "name": "Sijara Eubanks",
        "numericOdds": -400
      }
    },
    {
      "timestamp": "2021-07-24T07:05:00Z",
      "fighter1": {
        "name": "Elise Reed",
        "numericOdds": 300
      },
      "fighter2": {
        "name": "Sijara Eubanks",
        "numericOdds": -400
      }
    },
    {
      "timestamp": "2021-07-24T07:15:00Z",
      "fighter1": {
        "name": "Elise Reed",
        "numericOdds": 300
      },
      "fighter2": {
        "name": "Sijara Eubanks",
        "numericOdds": -400
      }
    },
    {
      "timestamp": "2021-07-24T07:25:00Z",
      "fighter1": {
        "name": "Elise Reed",
        "numericOdds": 300
      },
      "fighter2": {
        "name": "Sijara Eubanks",
        "numericOdds": -400
      }
    },
    {
      "timestamp": "2021-07-24T07:35:00Z",
      "fighter1": {
        "name": "Elise Reed",
        "numericOdds": 300
      },
      "fighter2": {
        "name": "Sijara Eubanks",
        "numericOdds": -400
      }
    },
    {
      "timestamp": "2021-07-24T07:45:00Z",
      "fighter1": {
        "name": "Elise Reed",
        "numericOdds": 300
      },
      "fighter2": {
        "name": "Sijara Eubanks",
        "numericOdds": -400
      }
    },
    {
      "timestamp": "2021-07-24T07:55:00Z",
      "fighter1": {
        "name": "Elise Reed",
        "numericOdds": 300
      },
      "fighter2": {
        "name": "Sijara Eubanks",
        "numericOdds": -400
      }
    },
    {
      "timestamp": "2021-07-24T08:05:00Z",
      "fighter1": {
        "name": "Elise Reed",
        "numericOdds": 300
      },
      "fighter2": {
        "name": "Sijara Eubanks",
        "numericOdds": -400
      }
    },
    {
      "timestamp": "2021-07-24T08:15:00Z",
      "fighter1": {
        "name": "Elise Reed",
        "numericOdds": 300
      },
      "fighter2": {
        "name": "Sijara Eubanks",
        "numericOdds": -400
      }
    },
    {
      "timestamp": "2021-07-24T08:25:00Z",
      "fighter1": {
        "name": "Elise Reed",
        "numericOdds": 300
      },
      "fighter2": {
        "name": "Sijara Eubanks",
        "numericOdds": -400
      }
    },
    {
      "timestamp": "2021-07-24T08:35:00Z",
      "fighter1": {
        "name": "Elise Reed",
        "numericOdds": 300
      },
      "fighter2": {
        "name": "Sijara Eubanks",
        "numericOdds": -400
      }
    },
    {
      "timestamp": "2021-07-24T08:45:00Z",
      "fighter1": {
        "name": "Elise Reed",
        "numericOdds": 300
      },
      "fighter2": {
        "name": "Sijara Eubanks",
        "numericOdds": -400
      }
    },
    {
      "timestamp": "2021-07-24T08:55:00Z",
      "fighter1": {
        "name": "Elise Reed",
        "numericOdds": 300
      },
      "fighter2": {
        "name": "Sijara Eubanks",
        "numericOdds": -400
      }
    },
    {
      "timestamp": "2021-07-24T09:05:00Z",
      "fighter1": {
        "name": "Elise Reed",
        "numericOdds": 300
      },
      "fighter2": {
        "name": "Sijara Eubanks",
        "numericOdds": -400
      }
    },
    {
      "timestamp": "2021-07-24T09:15:00Z",
      "fighter1": {
        "name": "Elise Reed",
        "numericOdds": 300
      },
      "fighter2": {
        "name": "Sijara Eubanks",
        "numericOdds": -400
      }
    },
    {
      "timestamp": "2021-07-24T09:25:00Z",
      "fighter1": {
        "name": "Elise Reed",
        "numericOdds": 300
      },
      "fighter2": {
        "name": "Sijara Eubanks",
        "numericOdds": -400
      }
    },
    {
      "timestamp": "2021-07-24T09:35:00Z",
      "fighter1": {
        "name": "Elise Reed",
        "numericOdds": 300
      },
      "fighter2": {
        "name": "Sijara Eubanks",
        "numericOdds": -400
      }
    },
    {
      "timestamp": "2021-07-24T09:45:00Z",
      "fighter1": {
        "name": "Elise Reed",
        "numericOdds": 300
      },
      "fighter2": {
        "name": "Sijara Eubanks",
        "numericOdds": -400
      }
    },
    {
      "timestamp": "2021-07-24T09:55:00Z",
      "fighter1": {
        "name": "Elise Reed",
        "numericOdds": 300
      },
      "fighter2": {
        "name": "Sijara Eubanks",
        "numericOdds": -400
      }
    },
    {
      "timestamp": "2021-07-24T10:05:00Z",
      "fighter1": {
        "name": "Elise Reed",
        "numericOdds": 300
      },
      "fighter2": {
        "name": "Sijara Eubanks",
        "numericOdds": -400
      }
    },
    {
      "timestamp": "2021-07-24T10:15:00Z",
      "fighter1": {
        "name": "Elise Reed",
        "numericOdds": 300
      },
      "fighter2": {
        "name": "Sijara Eubanks",
        "numericOdds": -400
      }
    },
    {
      "timestamp": "2021-07-24T10:25:00Z",
      "fighter1": {
        "name": "Elise Reed",
        "numericOdds": 300
      },
      "fighter2": {
        "name": "Sijara Eubanks",
        "numericOdds": -400
      }
    },
    {
      "timestamp": "2021-07-24T10:35:00Z",
      "fighter1": {
        "name": "Elise Reed",
        "numericOdds": 300
      },
      "fighter2": {
        "name": "Sijara Eubanks",
        "numericOdds": -400
      }
    },
    {
      "timestamp": "2021-07-24T10:45:00Z",
      "fighter1": {
        "name": "Elise Reed",
        "numericOdds": 300
      },
      "fighter2": {
        "name": "Sijara Eubanks",
        "numericOdds": -400
      }
    },
    {
      "timestamp": "2021-07-24T10:55:00Z",
      "fighter1": {
        "name": "Elise Reed",
        "numericOdds": 300
      },
      "fighter2": {
        "name": "Sijara Eubanks",
        "numericOdds": -400
      }
    },
    {
      "timestamp": "2021-07-24T11:05:00Z",
      "fighter1": {
        "name": "Elise Reed",
        "numericOdds": 300
      },
      "fighter2": {
        "name": "Sijara Eubanks",
        "numericOdds": -400
      }
    },
    {
      "timestamp": "2021-07-24T11:15:00Z",
      "fighter1": {
        "name": "Elise Reed",
        "numericOdds": 300
      },
      "fighter2": {
        "name": "Sijara Eubanks",
        "numericOdds": -400
      }
    },
    {
      "timestamp": "2021-07-24T11:25:00Z",
      "fighter1": {
        "name": "Elise Reed",
        "numericOdds": 300
      },
      "fighter2": {
        "name": "Sijara Eubanks",
        "numericOdds": -400
      }
    },
    {
      "timestamp": "2021-07-24T11:35:00Z",
      "fighter1": {
        "name": "Elise Reed",
        "numericOdds": 300
      },
      "fighter2": {
        "name": "Sijara Eubanks",
        "numericOdds": -400
      }
    },
    {
      "timestamp": "2021-07-24T11:45:00Z",
      "fighter1": {
        "name": "Elise Reed",
        "numericOdds": 300
      },
      "fighter2": {
        "name": "Sijara Eubanks",
        "numericOdds": -400
      }
    },
    {
      "timestamp": "2021-07-24T11:55:00Z",
      "fighter1": {
        "name": "Elise Reed",
        "numericOdds": 300
      },
      "fighter2": {
        "name": "Sijara Eubanks",
        "numericOdds": -400
      }
    },
    {
      "timestamp": "2021-07-24T12:05:00Z",
      "fighter1": {
        "name": "Elise Reed",
        "numericOdds": 300
      },
      "fighter2": {
        "name": "Sijara Eubanks",
        "numericOdds": -400
      }
    },
    {
      "timestamp": "2021-07-24T12:15:00Z",
      "fighter1": {
        "name": "Elise Reed",
        "numericOdds": 300
      },
      "fighter2": {
        "name": "Sijara Eubanks",
        "numericOdds": -400
      }
    },
    {
      "timestamp": "2021-07-24T12:25:00Z",
      "fighter1": {
        "name": "Elise Reed",
        "numericOdds": 300
      },
      "fighter2": {
        "name": "Sijara Eubanks",
        "numericOdds": -400
      }
    },
    {
      "timestamp": "2021-07-24T12:35:00Z",
      "fighter1": {
        "name": "Elise Reed",
        "numericOdds": 300
      },
      "fighter2": {
        "name": "Sijara Eubanks",
        "numericOdds": -400
      }
    },
    {
      "timestamp": "2021-07-24T12:45:00Z",
      "fighter1": {
        "name": "Elise Reed",
        "numericOdds": 300
      },
      "fighter2": {
        "name": "Sijara Eubanks",
        "numericOdds": -400
      }
    },
    {
      "timestamp": "2021-07-24T12:55:00Z",
      "fighter1": {
        "name": "Elise Reed",
        "numericOdds": 300
      },
      "fighter2": {
        "name": "Sijara Eubanks",
        "numericOdds": -400
      }
    },
    {
      "timestamp": "2021-07-24T13:05:00Z",
      "fighter1": {
        "name": "Elise Reed",
        "numericOdds": 300
      },
      "fighter2": {
        "name": "Sijara Eubanks",
        "numericOdds": -400
      }
    },
    {
      "timestamp": "2021-07-24T13:15:00Z",
      "fighter1": {
        "name": "Elise Reed",
        "numericOdds": 300
      },
      "fighter2": {
        "name": "Sijara Eubanks",
        "numericOdds": -400
      }
    },
    {
      "timestamp": "2021-07-24T13:25:00Z",
      "fighter1": {
        "name": "Elise Reed",
        "numericOdds": 300
      },
      "fighter2": {
        "name": "Sijara Eubanks",
        "numericOdds": -400
      }
    },
    {
      "timestamp": "2021-07-24T13:35:00Z",
      "fighter1": {
        "name": "Elise Reed",
        "numericOdds": 300
      },
      "fighter2": {
        "name": "Sijara Eubanks",
        "numericOdds": -400
      }
    },
    {
      "timestamp": "2021-07-24T13:45:00Z",
      "fighter1": {
        "name": "Elise Reed",
        "numericOdds": 300
      },
      "fighter2": {
        "name": "Sijara Eubanks",
        "numericOdds": -400
      }
    },
    {
      "timestamp": "2021-07-24T13:55:00Z",
      "fighter1": {
        "name": "Elise Reed",
        "numericOdds": 300
      },
      "fighter2": {
        "name": "Sijara Eubanks",
        "numericOdds": -400
      }
    },
    {
      "timestamp": "2021-07-24T14:05:00Z",
      "fighter1": {
        "name": "Elise Reed",
        "numericOdds": 300
      },
      "fighter2": {
        "name": "Sijara Eubanks",
        "numericOdds": -400
      }
    },
    {
      "timestamp": "2021-07-24T14:15:00Z",
      "fighter1": {
        "name": "Elise Reed",
        "numericOdds": 300
      },
      "fighter2": {
        "name": "Sijara Eubanks",
        "numericOdds": -400
      }
    },
    {
      "timestamp": "2021-07-24T14:25:00Z",
      "fighter1": {
        "name": "Elise Reed",
        "numericOdds": 300
      },
      "fighter2": {
        "name": "Sijara Eubanks",
        "numericOdds": -400
      }
    },
    {
      "timestamp": "2021-07-24T14:35:00Z",
      "fighter1": {
        "name": "Elise Reed",
        "numericOdds": 310
      },
      "fighter2": {
        "name": "Sijara Eubanks",
        "numericOdds": -417
      }
    },
    {
      "timestamp": "2021-07-24T14:45:00Z",
      "fighter1": {
        "name": "Elise Reed",
        "numericOdds": 310
      },
      "fighter2": {
        "name": "Sijara Eubanks",
        "numericOdds": -417
      }
    },
    {
      "timestamp": "2021-07-24T14:55:00Z",
      "fighter1": {
        "name": "Elise Reed",
        "numericOdds": 310
      },
      "fighter2": {
        "name": "Sijara Eubanks",
        "numericOdds": -417
      }
    },
    {
      "timestamp": "2021-07-24T15:05:00Z",
      "fighter1": {
        "name": "Elise Reed",
        "numericOdds": 310
      },
      "fighter2": {
        "name": "Sijara Eubanks",
        "numericOdds": -417
      }
    },
    {
      "timestamp": "2021-07-24T15:15:00Z",
      "fighter1": {
        "name": "Elise Reed",
        "numericOdds": 310
      },
      "fighter2": {
        "name": "Sijara Eubanks",
        "numericOdds": -417
      }
    },
    {
      "timestamp": "2021-07-24T15:25:00Z",
      "fighter1": {
        "name": "Elise Reed",
        "numericOdds": 310
      },
      "fighter2": {
        "name": "Sijara Eubanks",
        "numericOdds": -417
      }
    },
    {
      "timestamp": "2021-07-24T15:35:00Z",
      "fighter1": {
        "name": "Elise Reed",
        "numericOdds": 310
      },
      "fighter2": {
        "name": "Sijara Eubanks",
        "numericOdds": -417
      }
    },
    {
      "timestamp": "2021-07-24T15:45:00Z",
      "fighter1": {
        "name": "Elise Reed",
        "numericOdds": 310
      },
      "fighter2": {
        "name": "Sijara Eubanks",
        "numericOdds": -417
      }
    },
    {
      "timestamp": "2021-07-24T15:55:00Z",
      "fighter1": {
        "name": "Elise Reed",
        "numericOdds": 310
      },
      "fighter2": {
        "name": "Sijara Eubanks",
        "numericOdds": -417
      }
    },
    {
      "timestamp": "2021-07-24T16:05:00Z",
      "fighter1": {
        "name": "Elise Reed",
        "numericOdds": 310
      },
      "fighter2": {
        "name": "Sijara Eubanks",
        "numericOdds": -417
      }
    },
    {
      "timestamp": "2021-07-24T16:15:00Z",
      "fighter1": {
        "name": "Elise Reed",
        "numericOdds": 310
      },
      "fighter2": {
        "name": "Sijara Eubanks",
        "numericOdds": -417
      }
    },
    {
      "timestamp": "2021-07-24T16:25:00Z",
      "fighter1": {
        "name": "Elise Reed",
        "numericOdds": 310
      },
      "fighter2": {
        "name": "Sijara Eubanks",
        "numericOdds": -417
      }
    },
    {
      "timestamp": "2021-07-24T16:35:00Z",
      "fighter1": {
        "name": "Elise Reed",
        "numericOdds": 310
      },
      "fighter2": {
        "name": "Sijara Eubanks",
        "numericOdds": -417
      }
    },
    {
      "timestamp": "2021-07-24T16:45:00Z",
      "fighter1": {
        "name": "Elise Reed",
        "numericOdds": 310
      },
      "fighter2": {
        "name": "Sijara Eubanks",
        "numericOdds": -417
      }
    },
    {
      "timestamp": "2021-07-24T16:55:00Z",
      "fighter1": {
        "name": "Elise Reed",
        "numericOdds": 310
      },
      "fighter2": {
        "name": "Sijara Eubanks",
        "numericOdds": -417
      }
    },
    {
      "timestamp": "2021-07-24T17:05:00Z",
      "fighter1": {
        "name": "Elise Reed",
        "numericOdds": 310
      },
      "fighter2": {
        "name": "Sijara Eubanks",
        "numericOdds": -417
      }
    },
    {
      "timestamp": "2021-07-24T17:15:00Z",
      "fighter1": {
        "name": "Elise Reed",
        "numericOdds": 310
      },
      "fighter2": {
        "name": "Sijara Eubanks",
        "numericOdds": -417
      }
    },
    {
      "timestamp": "2021-07-24T17:25:00Z",
      "fighter1": {
        "name": "Elise Reed",
        "numericOdds": 310
      },
      "fighter2": {
        "name": "Sijara Eubanks",
        "numericOdds": -417
      }
    },
    {
      "timestamp": "2021-07-24T17:35:00Z",
      "fighter1": {
        "name": "Elise Reed",
        "numericOdds": 310
      },
      "fighter2": {
        "name": "Sijara Eubanks",
        "numericOdds": -417
      }
    },
    {
      "timestamp": "2021-07-24T17:45:00Z",
      "fighter1": {
        "name": "Elise Reed",
        "numericOdds": 310
      },
      "fighter2": {
        "name": "Sijara Eubanks",
        "numericOdds": -417
      }
    },
    {
      "timestamp": "2021-07-24T17:55:00Z",
      "fighter1": {
        "name": "Elise Reed",
        "numericOdds": 310
      },
      "fighter2": {
        "name": "Sijara Eubanks",
        "numericOdds": -417
      }
    },
    {
      "timestamp": "2021-07-24T18:05:00Z",
      "fighter1": {
        "name": "Elise Reed",
        "numericOdds": 310
      },
      "fighter2": {
        "name": "Sijara Eubanks",
        "numericOdds": -417
      }
    },
    {
      "timestamp": "2021-07-24T18:15:00Z",
      "fighter1": {
        "name": "Elise Reed",
        "numericOdds": 310
      },
      "fighter2": {
        "name": "Sijara Eubanks",
        "numericOdds": -417
      }
    },
    {
      "timestamp": "2021-07-24T18:25:00Z",
      "fighter1": {
        "name": "Elise Reed",
        "numericOdds": 310
      },
      "fighter2": {
        "name": "Sijara Eubanks",
        "numericOdds": -417
      }
    },
    {
      "timestamp": "2021-07-24T18:35:00Z",
      "fighter1": {
        "name": "Elise Reed",
        "numericOdds": 310
      },
      "fighter2": {
        "name": "Sijara Eubanks",
        "numericOdds": -417
      }
    },
    {
      "timestamp": "2021-07-24T18:45:00Z",
      "fighter1": {
        "name": "Elise Reed",
        "numericOdds": 310
      },
      "fighter2": {
        "name": "Sijara Eubanks",
        "numericOdds": -417
      }
    },
    {
      "timestamp": "2021-07-24T18:55:00Z",
      "fighter1": {
        "name": "Elise Reed",
        "numericOdds": 310
      },
      "fighter2": {
        "name": "Sijara Eubanks",
        "numericOdds": -417
      }
    },
    {
      "timestamp": "2021-07-24T19:05:00Z",
      "fighter1": {
        "name": "Elise Reed",
        "numericOdds": 310
      },
      "fighter2": {
        "name": "Sijara Eubanks",
        "numericOdds": -417
      }
    },
    {
      "timestamp": "2021-07-24T19:15:00Z",
      "fighter1": {
        "name": "Elise Reed",
        "numericOdds": 310
      },
      "fighter2": {
        "name": "Sijara Eubanks",
        "numericOdds": -417
      }
    },
    {
      "timestamp": "2021-07-24T19:25:00Z",
      "fighter1": {
        "name": "Elise Reed",
        "numericOdds": 310
      },
      "fighter2": {
        "name": "Sijara Eubanks",
        "numericOdds": -417
      }
    },
    {
      "timestamp": "2021-07-24T19:35:00Z",
      "fighter1": {
        "name": "Elise Reed",
        "numericOdds": 320
      },
      "fighter2": {
        "name": "Sijara Eubanks",
        "numericOdds": -417
      }
    },
    {
      "timestamp": "2021-07-24T19:45:00Z",
      "fighter1": {
        "name": "Elise Reed",
        "numericOdds": 320
      },
      "fighter2": {
        "name": "Sijara Eubanks",
        "numericOdds": -417
      }
    },
    {
      "timestamp": "2021-07-24T19:55:00Z",
      "fighter1": {
        "name": "Elise Reed",
        "numericOdds": 330
      },
      "fighter2": {
        "name": "Sijara Eubanks",
        "numericOdds": -435
      }
    },
    {
      "timestamp": "2021-07-24T20:05:00Z",
      "fighter1": {
        "name": "Elise Reed",
        "numericOdds": 330
      },
      "fighter2": {
        "name": "Sijara Eubanks",
        "numericOdds": -435
      }
    },
    {
      "timestamp": "2021-07-24T20:15:00Z",
      "fighter1": {
        "name": "Elise Reed",
        "numericOdds": 330
      },
      "fighter2": {
        "name": "Sijara Eubanks",
        "numericOdds": -435
      }
    },
    {
      "timestamp": "2021-07-24T20:25:00Z",
      "fighter1": {
        "name": "Elise Reed",
        "numericOdds": 330
      },
      "fighter2": {
        "name": "Sijara Eubanks",
        "numericOdds": -435
      }
    },
    {
      "timestamp": "2021-07-24T20:35:00Z",
      "fighter1": {
        "name": "Elise Reed",
        "numericOdds": 330
      },
      "fighter2": {
        "name": "Sijara Eubanks",
        "numericOdds": -435
      }
    },
    {
      "timestamp": "2021-07-24T20:45:00Z",
      "fighter1": {
        "name": "Elise Reed",
        "numericOdds": 320
      },
      "fighter2": {
        "name": "Sijara Eubanks",
        "numericOdds": -417
      }
    },
    {
      "timestamp": "2021-07-24T20:55:00Z",
      "fighter1": {
        "name": "Elise Reed",
        "numericOdds": 300
      },
      "fighter2": {
        "name": "Sijara Eubanks",
        "numericOdds": -400
      }
    },
    {
      "timestamp": "2021-07-24T21:05:00Z",
      "fighter1": {
        "name": "Elise Reed",
        "numericOdds": 500
      },
      "fighter2": {
        "name": "Sijara Eubanks",
        "numericOdds": -1000
      }
    }
  ]
}